Workbook

Sheet Historical
A1: Metric | B1: FY2022 | C1: FY2023 | D1: FY2024 | E1: FY2025 | F1: FY2026
A2: Net Sales | B2: 567762 | C2: 605881 | D2: 642637 | E2: 674538 | F2: 706413
A3: Cost of Sales | B3: 429000 | C3: 463721 | D3: 490142 | E3: 511753 | F3: 535395
A4: Gross Profit | B4: =B2-B3 -> 138762 | C4: =C2-C3 -> 142160 | D4: =D2-D3 -> 152495 | E4: =E2-E3 -> 162785 | F4: =F2-F3 -> 171018
A5: Operating Expenses | B5: 117812 | C5: 127140 | D5: 130971 | E5: 139884 | F5: 147943
A6: Operating Income(EBIT) | B6: =B4-B5 -> 20950 | C6: =C4-C5 -> 15020 | D6: =D4-D5 -> 21524 | E6: =E4-E5 -> 22901 | F6: =F4-F5 -> 23075
A7: Depreciation & Amortization | B7: 10658 | C7: 10945 | D7: 11853 | E7: 12973 | F7: 14203
A8: Interest Expense (net) | B8: 1836 | C8: 1874 | D8: 2137 | E8: 2245 | F8: 2431
A9: Income Tax Provision | B9: 4756 | C9: 5724 | D9: 5578 | E9: 6152 | F9: 7199
A10: Net income | B10: 13940 | C10: 11292 | D10: 16270 | E10: 20157 | F10: 22270
A11: Capital Expenditures | B11: 13106 | C11: 16857 | D11: 20606 | E11: 23783 | F11: 26672
A12: Operating Cash Flows | B12: 24181 | C12: 28841 | D12: 35726 | E12: 36443 | F12: 41565
A13: Gross Profit Margin % | B13: =B4/B2 -> 0.2444017 | C13: =C4/C2 -> 0.23463353 | D13: =D4/D2 -> 0.23729571 | E13: =E4/E2 -> 0.24132814 | F13: =F4/F2 -> 0.24209351
A14: Operating Income Margin % | B14: =B6/B2 -> 0.036899264 | C14: =C6/C2 -> 0.024790347 | D14: =D6/D2 -> 0.033493247 | E14: =E6/E2 -> 0.033950645 | F14: =F6/F2 -> 0.032665027
A15: Revenue Growth % | B15: x | C15: =(C2-B2)/B2 -> 0.067139048 | D15: =(D2-C2)/C2 -> 0.060665378 | E15: =(E2-D2)/D2 -> 0.049640777 | F15: =(F2-E2)/E2 -> 0.047254565

Sheet Assum
A1: DCF Assumptions - 3 Scenario Model
A3: Metric | B3: Bear Case | C3: Base Case | D3: Bull Case
A4: Revenue Growth Rate | B4: 3 | C4: 4.5 | D4: 6
A5: Gross profit Margin % | B5: 23 | C5: 24 | D5: 25
A6: Operating Expense margin % | B6: 20.5 | C6: 20.5 | D6: 19.5
A7: Tax Rate % | B7: 26 | C7: 24.5 | D7: 23
A8: CapEx as % of Revenue | B8: 3.5 | C8: 3.2 | D8: 3.2
A9: D&A as % of Revenue | B9: 1.9 | C9: 2 | D9: 2.1
A10: Discount Rate(WACC) | B10: 9 | C10: 8 | D10: 7
A11: Terminal Growth Rate | B11: 2 | C11: 2.5 | D11: 3

Sheet Projections
A1: Walmart Projected Income Statements
B3: FY2027 | C3: FY2028 | D3: FY2029 | E3: FY2030 | F3: FY2031
A4: Base Case
A5: Revenue | B5: =Historical!F2*(1+Assum!C4/100) -> 738201.58 | C5: =B5*(1+Assum!$C$4/100) -> 771420.66 | D5: =C5*(1+Assum!$C$4/100) -> 806134.59 | E5: =D5*(1+Assum!$C$4/100) -> 842410.64 | F5: =E5*(1+Assum!$C$4/100) -> 880319.12
A6: Gross Profit | B6: =B5*(Assum!$C$5/100) -> 177168.38 | C6: =C5*(Assum!$C$5/100) -> 185140.96 | D6: =D5*(Assum!$C$5/100) -> 193472.3 | E6: =E5*(Assum!$C$5/100) -> 202178.55 | F6: =F5*(Assum!$C$5/100) -> 211276.59
A7: Operating Expense | B7: =B5*(Assum!$C$6/100) -> 151331.32 | C7: =C5*(Assum!$C$6/100) -> 158141.23 | D7: =D5*(Assum!$C$6/100) -> 165257.59 | E7: =E5*(Assum!$C$6/100) -> 172694.18 | F7: =F5*(Assum!$C$6/100) -> 180465.42
A8: Operating Income(EBIT) | B8: =B6-B7 -> 25837.055 | C8: =C6-C7 -> 26999.723 | D8: =D6-D7 -> 28214.711 | E8: =E6-E7 -> 29484.372 | F8: =F6-F7 -> 30811.169
A9: Tax Expense | B9: =B8*(Assum!$C$7/100) -> 6330.0786 | C9: =C8*(Assum!$C$7/100) -> 6614.9321 | D9: =D8*(Assum!$C$7/100) -> 6912.6041 | E9: =E8*(Assum!$C$7/100) -> 7223.6713 | F9: =F8*(Assum!$C$7/100) -> 7548.7365
A10: NOPAT(Net Operating Profit after Taxes) | B10: =B8-B9 -> 19506.977 | C10: =C8-C9 -> 20384.791 | D10: =D8-D9 -> 21302.106 | E10: =E8-E9 -> 22260.701 | F10: =F8-F9 -> 23262.433
A11: D&A | B11: =B5*(Assum!$C$9/100) -> 14764.032 | C11: =C5*(Assum!$C$9/100) -> 15428.413 | D11: =D5*(Assum!$C$9/100) -> 16122.692 | E11: =E5*(Assum!$C$9/100) -> 16848.213 | F11: =F5*(Assum!$C$9/100) -> 17606.382
A12: CapEx | B12: =B5*(Assum!$C$8/100) -> 23622.451 | C12: =C5*(Assum!$C$8/100) -> 24685.461 | D12: =D5*(Assum!$C$8/100) -> 25796.307 | E12: =E5*(Assum!$C$8/100) -> 26957.141 | F12: =F5*(Assum!$C$8/100) -> 28170.212
A14: Bear Case
A15: Revenue | B15: =Historical!F2*(1+Assum!$B$4/100) -> 727605.39 | C15: =B15*(1+Assum!$B$4/100) -> 749433.55 | D15: =C15*(1+Assum!$B$4/100) -> 771916.56 | E15: =D15*(1+Assum!$B$4/100) -> 795074.05 | F15: =E15*(1+Assum!$B$4/100) -> 818926.28
A16: Gross Profit | B16: =B15*(Assum!$B$5/100) -> 167349.24 | C16: =C15*(Assum!$B$5/100) -> 172369.72 | D16: =D15*(Assum!$B$5/100) -> 177540.81 | E16: =E15*(Assum!$B$5/100) -> 182867.03 | F16: =F15*(Assum!$B$5/100) -> 188353.04
A17: Operating Expense | B17: =B15*(Assum!$B$6/100) -> 149159.1 | C17: =C15*(Assum!$B$6/100) -> 153633.88 | D17: =D15*(Assum!$B$6/100) -> 158242.89 | E17: =E15*(Assum!$B$6/100) -> 162990.18 | F17: =F15*(Assum!$B$6/100) -> 167879.89
A18: Operating Income(EBIT) | B18: =B16-B17 -> 18190.135 | C18: =C16-C17 -> 18735.839 | D18: =D16-D17 -> 19297.914 | E18: =E16-E17 -> 19876.851 | F18: =F16-F17 -> 20473.157
A19: Tax Expense | B19: =B18*(Assum!$B$7/100) -> 4729.435 | C19: =C18*(Assum!$B$7/100) -> 4871.3181 | D19: =D18*(Assum!$B$7/100) -> 5017.4576 | E19: =E18*(Assum!$B$7/100) -> 5167.9814 | F19: =F18*(Assum!$B$7/100) -> 5323.0208
A20: NOPAT | B20: =B18-B19 -> 13460.7 | C20: =C18-C19 -> 13864.521 | D20: =D18-D19 -> 14280.456 | E20: =E18-E19 -> 14708.87 | F20: =F18-F19 -> 15150.136
A21: D&A | B21: =B15*(Assum!$B$9/100) -> 13824.502 | C21: =C15*(Assum!$B$9/100) -> 14239.237 | D21: =D15*(Assum!$B$9/100) -> 14666.415 | E21: =E15*(Assum!$B$9/100) -> 15106.407 | F21: =F15*(Assum!$B$9/100) -> 15559.599
A22: Capex | B22: =B15*(Assum!$B$8/100) -> 25466.189 | C22: =C15*(Assum!$B$8/100) -> 26230.174 | D22: =D15*(Assum!$B$8/100) -> 27017.08 | E22: =E15*(Assum!$B$8/100) -> 27827.592 | F22: =F15*(Assum!$B$8/100) -> 28662.42
A24: Bull Case
A25: Revenue | B25: =Historical!F2*(1+Assum!$D$4/100) -> 748797.78 | C25: =B25*(1+Assum!$D$4/100) -> 793725.65 | D25: =C25*(1+Assum!$D$4/100) -> 841349.19 | E25: =D25*(1+Assum!$D$4/100) -> 891830.14 | F25: =E25*(1+Assum!$D$4/100) -> 945339.94
A26: Gross Profit | B26: =B25*(Assum!$D$5/100) -> 187199.45 | C26: =C25*(Assum!$D$5/100) -> 198431.41 | D26: =D25*(Assum!$D$5/100) -> 210337.3 | E26: =E25*(Assum!$D$5/100) -> 222957.53 | F26: =F25*(Assum!$D$5/100) -> 236334.99
A27: Operating Expense | B27: =B25*(Assum!$D$6/100) -> 146015.57 | C27: =C25*(Assum!$D$6/100) -> 154776.5 | D27: =D25*(Assum!$D$6/100) -> 164063.09 | E27: =E25*(Assum!$D$6/100) -> 173906.88 | F27: =F25*(Assum!$D$6/100) -> 184341.29
A28: Operating Income(EBIT) | B28: =B26-B27 -> 41183.878 | C28: =C26-C27 -> 43654.911 | D28: =D26-D27 -> 46274.205 | E28: =E26-E27 -> 49050.658 | F28: =F26-F27 -> 51993.697
A29: Tax Expense | B29: =B28*(Assum!$D$7/100) -> 9472.2919 | C29: =C28*(Assum!$D$7/100) -> 10040.629 | D29: =D28*(Assum!$D$7/100) -> 10643.067 | E29: =E28*(Assum!$D$7/100) -> 11281.651 | F29: =F28*(Assum!$D$7/100) -> 11958.55
A30: NOPAT | B30: =B28-B29 -> 31711.586 | C30: =C28-C29 -> 33614.281 | D30: =D28-D29 -> 35631.138 | E30: =E28-E29 -> 37769.006 | F30: =F28-F29 -> 40035.147
A31: D&A | B31: =B25*(Assum!$D$9/100) -> 15724.753 | C31: =C25*(Assum!$D$9/100) -> 16668.239 | D31: =D25*(Assum!$D$9/100) -> 17668.333 | E31: =E25*(Assum!$D$9/100) -> 18728.433 | F31: =F25*(Assum!$D$9/100) -> 19852.139
A32: CapEx | B32: =B25*(Assum!$D$8/100) -> 23961.529 | C32: =C25*(Assum!$D$8/100) -> 25399.221 | D32: =D25*(Assum!$D$8/100) -> 26923.174 | E32: =E25*(Assum!$D$8/100) -> 28538.564 | F32: =F25*(Assum!$D$8/100) -> 30250.878

Sheet FCF
A1: Free Cash Flow Build
A3: Base Case | B3: FY2027 | C3: FY2028 | D3: FY2029 | E3: FY2030 | F3: FY2031
A4: NOPAT | B4: =Projections!B10 -> 19506.977 | C4: =Projections!C10 -> 20384.791 | D4: =Projections!D10 -> 21302.106 | E4: =Projections!E10 -> 22260.701 | F4: =Projections!F10 -> 23262.433
A5: Add Back D&A | B5: =Projections!B11 -> 14764.032 | C5: =Projections!C11 -> 15428.413 | D5: =Projections!D11 -> 16122.692 | E5: =Projections!E11 -> 16848.213 | F5: =Projections!F11 -> 17606.382
A6: Less CapEx | B6: =Projections!B12 -> 23622.451 | C6: =Projections!C12 -> 24685.461 | D6: =Projections!D12 -> 25796.307 | E6: =Projections!E12 -> 26957.141 | F6: =Projections!F12 -> 28170.212
A7: Unlevered Free Cash Flow | B7: =B4+B5-B6 -> 10648.558 | C7: =C4+C5-C6 -> 11127.743 | D7: =D4+D5-D6 -> 11628.491 | E7: =E4+E5-E6 -> 12151.774 | F7: =F4+F5-F6 -> 12698.603
A9: Bear Case
A10: NOPAT | B10: =Projections!B20 -> 13460.7 | C10: =Projections!C20 -> 13864.521 | D10: =Projections!D20 -> 14280.456 | E10: =Projections!E20 -> 14708.87 | F10: =Projections!F20 -> 15150.136
A11: Add Back D&A | B11: =Projections!B21 -> 13824.502 | C11: =Projections!C21 -> 14239.237 | D11: =Projections!D21 -> 14666.415 | E11: =Projections!E21 -> 15106.407 | F11: =Projections!F21 -> 15559.599
A12: Less CapEx | B12: =Projections!B22 -> 25466.189 | C12: =Projections!C22 -> 26230.174 | D12: =Projections!D22 -> 27017.08 | E12: =Projections!E22 -> 27827.592 | F12: =Projections!F22 -> 28662.42
A13: Unlevered Free Cash Flows | B13: =B10+B11-B12 -> 1819.0135 | C13: =C10+C11-C12 -> 1873.5839 | D13: =D10+D11-D12 -> 1929.7914 | E13: =E10+E11-E12 -> 1987.6851 | F13: =F10+F11-F12 -> 2047.3157
A15: Bull Case
A16: NOPAT | B16: =Projections!B30 -> 31711.586 | C16: =Projections!C30 -> 33614.281 | D16: =Projections!D30 -> 35631.138 | E16: =Projections!E30 -> 37769.006 | F16: =Projections!F30 -> 40035.147
A17: Add Back D&A | B17: =Projections!B31 -> 15724.753 | C17: =Projections!C31 -> 16668.239 | D17: =Projections!D31 -> 17668.333 | E17: =Projections!E31 -> 18728.433 | F17: =Projections!F31 -> 19852.139
A18: Less CapEx | B18: =Projections!B32 -> 23961.529 | C18: =Projections!C32 -> 25399.221 | D18: =Projections!D32 -> 26923.174 | E18: =Projections!E32 -> 28538.564 | F18: =Projections!F32 -> 30250.878
A19: Unlevered Free Cash Flow | B19: =B16+B17-B18 -> 23474.81 | C19: =C16+C17-C18 -> 24883.299 | D19: =D16+D17-D18 -> 26376.297 | E19: =E16+E17-E18 -> 27958.875 | F19: =F16+F17-F18 -> 29636.407

Sheet DCF Valuation
A1: DCF Valuations - Base Case
A3: Year | B3: FY2027 | C3: FY2028 | D3: FY2029 | E3: FY2030 | F3: FY2031 | I3: Scenario | J3: Implied Shares price
A4: UFCF | B4: =FCF!B7 -> 10648.558 | C4: =FCF!C7 -> 11127.743 | D4: =FCF!D7 -> 11628.491 | E4: =FCF!E7 -> 12151.774 | F4: =FCF!F7 -> 12698.603 | I4: Bear Case | J4: =B32 -> 0.36893785
A5: Discount Factor | B5: =1/(1+Assum!$C$10/100)^1 -> 0.92592593 | C5: =1/(1+Assum!$C$10/100)^2 -> 0.85733882 | D5: =1/(1+Assum!$C$10/100)^3 -> 0.79383224 | E5: =1/(1+Assum!$C$10/100)^4 -> 0.73502985 | F5: =1/(1+Assum!$C$10/100)^5 -> 0.6805832 | I5: Base Case | J5: =B15 -> 22.804678
A6: Present Value of UFCF | B6: =B4*B5 -> 9859.7758 | C6: =C4*C5 -> 9540.246 | D6: =D4*D5 -> 9231.0714 | E6: =E4*E5 -> 8931.9163 | F6: =F4*F5 -> 8642.456 | I6: Bull Case | J6: =B49 -> 78.084013
A8: Sum of PV of Cash Flows | B8: =SUM(B6:F6) -> 46205.466
A9: Terminal Value | B9: =(F4*(1+Assum!$C$11/100))/(Assum!$C$10/100-Assum!$C$11/100) -> 236655.79 | I9: Scenario | J9: Implied Share Price | K9: Current Share Price | L9: Upside/Downside
A10: PV of Terminal Value | B10: =B9*F5 -> 161063.95 | I10: Bear Case | J10: =J4 -> 0.36893785 | K10: 118.72 | L10: =J10/K10-1 -> -0.99689237
A11: Enterprise Value | B11: =B8+B10 -> 207269.42 | I11: Base Case | J11: =J5 -> 22.804678 | K11: 118.72 | L11: =J11/K11-1 -> -0.80791208
A12: Less net Debt | B12: =34624-10727 -> 23897 | I12: Bull Case | J12: =J6 -> 78.084013 | K12: 118.72 | L12: =J12/K12-1 -> -0.34228426
A13: Equity Value | B13: =B11-B12 -> 183372.42
A14: Shares Outstanding | B14: =8041 -> 8041
A15: Implied Share Price | B15: =B13/B14 -> 22.804678 | I15: Recommendation | J15: Sell/Overvalued
I16: Reason | J16: Base Case DCF Value is below current market price
A18: DCF Valuations - Bear Case | I18: Key Takeaway | J18: Walmart appears overvalued under my current DCF Assumptions, as the Base Case Implied share price is below the current market price.
A20: Year | B20: FY2027 | C20: FY2028 | D20: FY2029 | E20: FY2030 | F20: FY2031
A21: CFCF | B21: =FCF!B13 -> 1819.0135 | C21: =FCF!C13 -> 1873.5839 | D21: =FCF!D13 -> 1929.7914 | E21: =FCF!E13 -> 1987.6851 | F21: =FCF!F13 -> 2047.3157
A22: Discount Factor | B22: =1/(1+Assum!$B$10/100)^1 -> 0.91743119 | C22: =1/(1+Assum!B$10/100)^2 -> 0.84167999 | D22: =1/(1+Assum!$B$10/100)^3 -> 0.77218348 | E22: =1/(1+Assum!$B$10/100)^4 -> 0.70842521 | F22: =1/(1+Assum!$B$10/100)^5 -> 0.64993139
A23: Present Value of UFCF | B23: =B21*B22 -> 1668.8197 | C23: =C21*C22 -> 1576.9581 | D23: =D21*D22 -> 1490.153 | E23: =E21*E22 -> 1408.1263 | F23: =F21*F22 -> 1330.6147
A25: Sum of PV of Cash Flows | B25: =SUM(B23:F23) -> 7474.6718
A26: Terminal Value | B26: =(F21*(1+Assum!$B$11/100))/(Assum!$B$10/100-Assum!$B$11/100) -> 29832.314
A27: PV of Terminal Value | B27: =B26*F22 -> 19388.957
A28: Enterprise Value | B28: =B25+B27 -> 26863.629
A29: Less Net Debt | B29: 23897
A30: Equity Value | B30: =B28-B29 -> 2966.6292
A31: Shares Outstanding | B31: =8041 -> 8041
A32: Implied Share Price | B32: =B30/B31 -> 0.36893785
A35: DCF Valuations - Bull Case
A37: Year | B37: FY2027 | C37: FY2028 | D37: FY2029 | E37: FY2030 | F37: FY2031
A38: UFCF | B38: =FCF!B19 -> 23474.81 | C38: =FCF!C19 -> 24883.299 | D38: =FCF!D19 -> 26376.297 | E38: =FCF!E19 -> 27958.875 | F38: =FCF!F19 -> 29636.407
A39: Discount Factor | B39: =1/(1+Assum!$D$10/100)^1 -> 0.93457944 | C39: =1/(1+Assum!$D$10/100)^2 -> 0.87343873 | D39: =1/(1+Assum!$D$10/100)^3 -> 0.81629788 | E39: =1/(1+Assum!$D10/100)^4 -> 0.76289521 | F39: =1/(1+Assum!$D$10/100)^5 -> 0.71298618
A40: Present value of UFCF | B40: =B38*B39 -> 21939.075 | C40: =C38*C39 -> 21734.037 | D40: =D38*D39 -> 21530.915 | E40: =E38*E39 -> 21329.692 | F40: =F38*F39 -> 21130.349
A42: Sum of PV of Cash Flows | B42: =SUM(B40:F40) -> 107664.07
A43: Terminal Value | B43: =(F38*(1+Assum!$D$11/100))/(Assum!$D$10/100-Assum!$D$11/100) -> 763137.49
A44: PV of Terminal Value | B44: =B43*F39 -> 544106.48
A45: Enterprise Value | B45: =B42+B44 -> 651770.55
A46: Less Net Debt | B46: =23897 -> 23897
A47: Equity Value | B47: =B45-B46 -> 627873.55
A48: Shares Outstanding | B48: =8041 -> 8041
A49: Implied Share Price | B49: =B47/B48 -> 78.084013
